python_mermaid/__init__.py
python_mermaid/diagram.py
python_mermaid/interaction.py
python_mermaid/link.py
python_mermaid/node.py
python_mermaid/utils.py
python_mermaid-0.1.6.dist-info/LICENSE
python_mermaid-0.1.6.dist-info/METADATA
python_mermaid-0.1.6.dist-info/WHEEL
python_mermaid-0.1.6.dist-info/RECORD
