Metadata-Version: 2.3
Name: python_mermaid
Version: 0.1.6
Summary: A (quite) simple that helps creating on-the-fly Mermaid diagrams
Author: Dynnammo
Author-email: contact@dynnammo.com
Requires-Python: >=3.10,<4.0
Classifier: Programming Language :: Python :: 3
Classifier: Programming Language :: Python :: 3.10
Classifier: Programming Language :: Python :: 3.11
Classifier: Programming Language :: Python :: 3.12
Classifier: Programming Language :: Python :: 3.13
Requires-Dist: Unidecode (>=1.3.6,<2.0.0)
Requires-Dist: mypy (>=1.16.0,<2.0.0)
Requires-Dist: pre-commit (>=4.2.0,<5.0.0)
